bSecure/__init__.py
bSecure/base.py
bSecure/authentication/__init__.py
bSecure/authentication/builder_authentication.py
bSecure/authentication/exceptions.py
bSecure/authentication/single_sign_on.py
bSecure/buttons/__init__.py
bSecure/buttons/buttons.py
bSecure/exceptions/__init__.py
bSecure/exceptions/base.py
bSecure/helpers/__init__.py
bSecure/helpers/constants.py
bSecure/helpers/utils.py
bSecure/order_management/__init__.py
bSecure/order_management/order_management.py
tests/__init__.py
bSecure-0.0.0.6.3.dist-info/METADATA
bSecure-0.0.0.6.3.dist-info/WHEEL
bSecure-0.0.0.6.3.dist-info/top_level.txt
bSecure-0.0.0.6.3.dist-info/RECORD
