Metadata-Version: 2.1
Name: bSecure
Version: 0.0.0.6.3
Summary: bSecure is a Universal Checkout for Pakistan (Alpha Release)
Home-page: https://bsecure.pk
Author: bSecure
Author-email: tech@bsecure.pk
License: MIT
Platform: UNKNOWN
Classifier: Development Status :: 3 - Alpha
Classifier: Intended Audience :: Developers
Classifier: Topic :: Software Development :: Build Tools
Classifier: License :: OSI Approved :: MIT License
Classifier: Programming Language :: Python :: 3.5
Classifier: Programming Language :: Python :: 3.6
Classifier: Programming Language :: Python :: 3.7
Classifier: Programming Language :: Python :: 3.8
Classifier: Programming Language :: Python :: 3.9
Requires-Python: >=3.5
Requires-Dist: requests
